MANIFEST.in
README.md
setup.py
anthill/login/__init__.py
anthill/login/admin.py
anthill/login/handler.py
anthill/login/options.py
anthill/login/server.py
anthill/login/model/__init__.py
anthill/login/model/access.py
anthill/login/model/account.py
anthill/login/model/authenticator.py
anthill/login/model/credential.py
anthill/login/model/gamespace.py
anthill/login/model/key.py
anthill/login/model/password.py
anthill/login/model/token.py
anthill/login/social/__init__.py
anthill/login/social/facebook.py
anthill/login/social/gamecenter.py
anthill/login/social/google.py
anthill/login/social/mailru.py
anthill/login/social/steam.py
anthill/login/social/vk.py
anthill/login/sql/account_access.sql
anthill/login/sql/account_credentials.sql
anthill/login/sql/accounts.sql
anthill/login/sql/credential_passwords.sql
anthill/login/sql/gamespace.sql
anthill/login/sql/gamespace_aliases.sql
anthill/login/sql/gamespace_keys.sql
anthill/login/static/css/bootstrap.min.css
anthill/login/static/css/font-awesome.min.css
anthill/login/static/css/login-modal.css
anthill/login/static/css/open-sans.css
anthill/login/static/css/style.css
anthill/login/static/fonts/FontAwesome.otf
anthill/login/static/fonts/fontawesome-webfont.eot
anthill/login/static/fonts/fontawesome-webfont.svg
anthill/login/static/fonts/fontawesome-webfont.ttf
anthill/login/static/fonts/fontawesome-webfont.woff
anthill/login/static/fonts/fontawesome-webfont.woff2
anthill/login/static/fonts/glyphicons-halflings-regular.eot
anthill/login/static/fonts/glyphicons-halflings-regular.svg
anthill/login/static/fonts/glyphicons-halflings-regular.ttf
anthill/login/static/fonts/glyphicons-halflings-regular.woff
anthill/login/static/fonts/glyphicons-halflings-regular.woff2
anthill/login/static/fonts/opensans/59ZRklaO5bWGqF5A9baEEYX0hVgzZQUfRDuZrPvH3D8.woff2
anthill/login/static/fonts/opensans/K88pR3goAWT7BTt32Z01m4X0hVgzZQUfRDuZrPvH3D8.woff2
anthill/login/static/fonts/opensans/LWCjsQkB6EMdfHrEVqA1KYX0hVgzZQUfRDuZrPvH3D8.woff2
anthill_login.egg-info/PKG-INFO
anthill_login.egg-info/SOURCES.txt
anthill_login.egg-info/dependency_links.txt
anthill_login.egg-info/namespace_packages.txt
anthill_login.egg-info/not-zip-safe
anthill_login.egg-info/requires.txt
anthill_login.egg-info/top_level.txt