Metadata-Version: 1.0
Name: anthill-login
Version: 0.2
Summary: An authentication service for Anthill platform
Home-page: https://github.com/anthill-platform/anthill-login
Author: desertkun
Author-email: desertkun@gmail.com
License: MIT
Platform: UNKNOWN
